sopel_modules.tableflip-0.1.2-nspkg.pth
sopel_modules/tableflip/__init__.py
sopel_modules/tableflip/tableflip.py
sopel_modules.tableflip-0.1.2.dist-info/DESCRIPTION.rst
sopel_modules.tableflip-0.1.2.dist-info/METADATA
sopel_modules.tableflip-0.1.2.dist-info/RECORD
sopel_modules.tableflip-0.1.2.dist-info/WHEEL
sopel_modules.tableflip-0.1.2.dist-info/metadata.json
sopel_modules.tableflip-0.1.2.dist-info/namespace_packages.txt
sopel_modules.tableflip-0.1.2.dist-info/top_level.txt
tests/__init__.py
tests/requirements.txt
tests/test_tableflip.py
tests/.ropeproject/config.py
tests/.ropeproject/globalnames
tests/.ropeproject/history
tests/.ropeproject/objectdb
