Metadata-Version: 2.0
Name: sopel-modules.tableflip
Version: 0.1.2
Summary: TableFlip module for Sopel
Home-page: https://github.com/hemna/sopel-tableflip
Author: Walter A. Boring IV
Author-email: waboring@hemna.com
License: Eiffel Forum License, version 2
Platform: UNKNOWN
Requires-Dist: bottle
Requires-Dist: sopel (<7,>=6.0)
